static_sitemap/__init__.py
static_sitemap/__main__.py
static_sitemap/lib.py
static_sitemap-1.0.5.dist-info/licenses/LICENSE
static_sitemap-1.0.5.dist-info/METADATA
static_sitemap-1.0.5.dist-info/WHEEL
static_sitemap-1.0.5.dist-info/top_level.txt
static_sitemap-1.0.5.dist-info/RECORD
