Metadata-Version: 2.4
Name: static-sitemap
Version: 1.0.5
Summary: Create a sitemap from an url
Author-email: n4n5 <its.just.n4n5@gmail.com>
License-Expression: MIT
Project-URL: Homepage, https://github.com/its-just-nans/static-sitemap
Project-URL: Bug Tracker, https://github.com/its-just-nans/static-sitemap/issues
Keywords: sitemap,static,python,static-sitemap,static_sitemap,generator,sitemap-generator
Classifier: Programming Language :: Python
Classifier: Programming Language :: Python :: 3
Requires-Python: >=3.6
License-File: LICENSE
Dynamic: license-file
